histogramming/__init__.py
histogramming/histogram.py
histogramming/test_histogram.py
histogramming-0.1.1.dist-info/LICENSE
histogramming-0.1.1.dist-info/METADATA
histogramming-0.1.1.dist-info/WHEEL
histogramming-0.1.1.dist-info/top_level.txt
histogramming-0.1.1.dist-info/RECORD
